buildbot/VERSION
buildbot/__init__.py
buildbot/buildbot_net_usage_data.py
buildbot/buildrequest.py
buildbot/errors.py
buildbot/interfaces.py
buildbot/locks.py
buildbot/manhole.py
buildbot/master.py
buildbot/pbutil.py
buildbot/revlinks.py
buildbot/scheduler.py
buildbot/warnings.py
buildbot/changes/__init__.py
buildbot/changes/base.py
buildbot/changes/bitbucket.py
buildbot/changes/changes.py
buildbot/changes/filter.py
buildbot/changes/gerritchangesource.py
buildbot/changes/github.py
buildbot/changes/gitpoller.py
buildbot/changes/hgpoller.py
buildbot/changes/mail.py
buildbot/changes/manager.py
buildbot/changes/p4poller.py
buildbot/changes/pb.py
buildbot/changes/svnpoller.py
buildbot/clients/__init__.py
buildbot/clients/sendchange.py
buildbot/clients/tryclient.py
buildbot/clients/usersclient.py
buildbot/config/__init__.py
buildbot/config/builder.py
buildbot/config/checks.py
buildbot/config/errors.py
buildbot/config/master.py
buildbot/configurators/__init__.py
buildbot/configurators/janitor.py
buildbot/data/__init__.py
buildbot/data/base.py
buildbot/data/build_data.py
buildbot/data/builders.py
buildbot/data/buildrequests.py
buildbot/data/builds.py
buildbot/data/buildsets.py
buildbot/data/changes.py
buildbot/data/changesources.py
buildbot/data/codebase_branches.py
buildbot/data/codebase_commits.py
buildbot/data/codebases.py
buildbot/data/connector.py
buildbot/data/exceptions.py
buildbot/data/forceschedulers.py
buildbot/data/logchunks.py
buildbot/data/logs.py
buildbot/data/masters.py
buildbot/data/patches.py
buildbot/data/projects.py
buildbot/data/properties.py
buildbot/data/resultspec.py
buildbot/data/root.py
buildbot/data/schedulers.py
buildbot/data/sourcestamps.py
buildbot/data/steps.py
buildbot/data/test_result_sets.py
buildbot/data/test_results.py
buildbot/data/types.py
buildbot/data/workers.py
buildbot/db/__init__.py
buildbot/db/base.py
buildbot/db/build_data.py
buildbot/db/builders.py
buildbot/db/buildrequests.py
buildbot/db/builds.py
buildbot/db/buildsets.py
buildbot-4.3.0.dist-info/COPYING
buildbot-4.3.0.dist-info/METADATA
buildbot-4.3.0.dist-info/WHEEL
buildbot-4.3.0.dist-info/entry_points.txt
buildbot-4.3.0.dist-info/top_level.txt
buildbot-4.3.0.dist-info/RECORD
