Metadata-Version: 2.1
Name: buildbot
Version: 4.3.0
Summary: The Continuous Integration Framework
Home-page: http://buildbot.net/
Author: Brian Warner
Author-email: warner-buildbot@lothar.com
Maintainer: Dustin J. Mitchell
Maintainer-email: dustin@v.igoro.us
Classifier: Development Status :: 5 - Production/Stable
Classifier: Environment :: No Input/Output (Daemon)
Classifier: Environment :: Web Environment
Classifier: Intended Audience :: Developers
Classifier: License :: OSI Approved :: GNU General Public License v2 (GPLv2)
Classifier: Topic :: Software Development :: Build Tools
Classifier: Topic :: Software Development :: Testing
Classifier: Programming Language :: Python :: 3
Classifier: Programming Language :: Python :: 3.9
Classifier: Programming Language :: Python :: 3.10
Classifier: Programming Language :: Python :: 3.11
Classifier: Programming Language :: Python :: 3.12
Classifier: Programming Language :: Python :: 3.13
License-File: COPYING
Requires-Dist: setuptools>=8.0
Requires-Dist: Twisted>=22.1.0
Requires-Dist: treq>=20.9
Requires-Dist: Jinja2>=2.1
Requires-Dist: msgpack>=0.6.0
Requires-Dist: croniter>=1.3.0
Requires-Dist: importlib-resources>=5; python_version < "3.9"
Requires-Dist: zope.interface>=4.1.1
Requires-Dist: sqlalchemy>=1.4.0
Requires-Dist: alembic>=1.6.0
Requires-Dist: python-dateutil>=1.5
Requires-Dist: txaio>=2.2.2
Requires-Dist: autobahn>=0.16.0
Requires-Dist: packaging
Requires-Dist: PyJWT
Requires-Dist: pyyaml
Requires-Dist: unidiff>=0.7.5
Provides-Extra: test
Requires-Dist: setuptools_trial; extra == "test"
Requires-Dist: ruff; extra == "test"
Requires-Dist: treq; extra == "test"
Requires-Dist: txrequests; extra == "test"
Requires-Dist: pypugjs; extra == "test"
Requires-Dist: boto3; extra == "test"
Requires-Dist: moto; extra == "test"
Requires-Dist: Markdown>=3.0.0; extra == "test"
Requires-Dist: parameterized; extra == "test"
Requires-Dist: lz4; extra == "test"
Provides-Extra: bundle
Requires-Dist: buildbot-www==4.3.0; extra == "bundle"
Requires-Dist: buildbot-worker==4.3.0; extra == "bundle"
Requires-Dist: buildbot-waterfall-view==4.3.0; extra == "bundle"
Requires-Dist: buildbot-console-view==4.3.0; extra == "bundle"
Requires-Dist: buildbot-grid-view==4.3.0; extra == "bundle"
Provides-Extra: tls
Requires-Dist: Twisted[tls]>=22.1.0; extra == "tls"
Requires-Dist: pyopenssl>=16.0.0; extra == "tls"
Requires-Dist: service_identity; extra == "tls"
Requires-Dist: idna>=0.6; extra == "tls"
Provides-Extra: docs
Requires-Dist: docutils>=0.16.0; extra == "docs"
Requires-Dist: sphinx>=3.2.0; extra == "docs"
Requires-Dist: sphinx-rtd-theme>=0.5; extra == "docs"
Requires-Dist: sphinxcontrib-spelling; extra == "docs"
Requires-Dist: sphinxcontrib-websupport; extra == "docs"
Requires-Dist: pyenchant; extra == "docs"
Requires-Dist: sphinx-jinja; extra == "docs"
Requires-Dist: towncrier; extra == "docs"
Provides-Extra: brotli
Requires-Dist: Brotli>=1.1.0; extra == "brotli"
Provides-Extra: zstd
Requires-Dist: zstandard>=0.23.0; extra == "zstd"
Provides-Extra: configurable
Requires-Dist: evalidate>=2.0.0; extra == "configurable"
